[
  {
    "q_id": 1,
    "text": "Имеется ли опыт обучения в дистанционном формате?",
    "ans": [
      {
        "ans_id": 1,
        "text": "Нет"
      },
      {
        "ans_id": 2,
        "text": "Да"
      }
    ]
  },
  {
    "q_id": 2,
    "text": "Как Вы считаете можно ли получить качественные знания при обучении в онлайн формате? ",
    "ans": [
      {
        "ans_id": 1,
        "text": "Нет"
      },
      {
        "ans_id": 2,
        "text": "Да"
      }
    ]
  },
  {
    "q_id": 3,
    "text": "Оцените уровень удовлетворенности распределением времени дистанционного обучения в неделю по шкале от 1 до 5, где 1 - совсем не удовлетворен, 5 - полностью удовлетворен).",
    "ans": [
      {
        "ans_id": 1,
        "text": "1"
      },
      {
        "ans_id": 2,
        "text": "2"
      },
      {
        "ans_id": 3,
        "text": "3"
      },
      {
        "ans_id": 4,
        "text": "4"
      },
      {
        "ans_id": 5,
        "text": "5"
      }
    ]
  },
  {
    "q_id": 4,
    "text": "Оцените уровень технической организации обучения в дистанционном формате по шкале от 1 до 5, где 1 - совсем не удовлетворен, 5 - полностью удовлетворен).",
    "ans": [
      {
        "ans_id": 1,
        "text": "1"
      },
      {
        "ans_id": 2,
        "text": "2"
      },
      {
        "ans_id": 3,
        "text": "3"
      },
      {
        "ans_id": 4,
        "text": "4"
      },
      {
        "ans_id": 5,
        "text": "5"
      }
    ]
  },
  {
    "q_id": 5,
    "text": "Имели ли Вы ранее опыт обучения через образовательные платформы, СДО?",
    "ans": [
      {
        "ans_id": 1,
        "text": "Нет"
      },
      {
        "ans_id": 2,
        "text": "Да"
      }
    ]
  },
  {
    "q_id": 6,
    "text": "Оцените уровень удобства использования СДО по шкале от 1 до 5, где 1 - совсем не удовлетворен, 5 - полностью удовлетворен).",
    "ans": [
      {
        "ans_id": 1,
        "text": "1"
      },
      {
        "ans_id": 2,
        "text": "2"
      },
      {
        "ans_id": 3,
        "text": "3"
      },
      {
        "ans_id": 4,
        "text": "4"
      },
      {
        "ans_id": 5,
        "text": "5"
      }
    ]
  },
  {
    "q_id": 7,
    "text": "Оцените уровень методического сопровождения  обучения в дистанционном формате по шкале от 1 до 5, где 1 - совсем не удовлетворен, 5 - полностью удовлетворен).",
    "ans": [
      {
        "ans_id": 1,
        "text": "1"
      },
      {
        "ans_id": 2,
        "text": "2"
      },
      {
        "ans_id": 3,
        "text": "3"
      },
      {
        "ans_id": 4,
        "text": "4"
      },
      {
        "ans_id": 5,
        "text": "5"
      }
    ]
  },
  {
    "q_id": 8,
    "text": "Применялся ли при обучении формат видеолекций?",
    "ans": [
      {
        "ans_id": 1,
        "text": "Нет"
      },
      {
        "ans_id": 2,
        "text": "Да"
      }
    ]
  },
  {
    "q_id": 9,
    "text": "Оцените качество видеоконтента по шкале  от 1 до 5, где 1 - совсем не удовлетворен, 5 - полностью удовлетворен).",
    "ans": [
      {
        "ans_id": 1,
        "text": "1"
      },
      {
        "ans_id": 2,
        "text": "2"
      },
      {
        "ans_id": 3,
        "text": "3"
      },
      {
        "ans_id": 4,
        "text": "4"
      },
      {
        "ans_id": 5,
        "text": "5"
      }
    ]
  },
  {
    "q_id": 10,
    "text": "Оцените качество преподавания (владение учебным материалом, умение изложить его понятно, четко, логично и доступно)  по шкале от 1 до 5, где 1 - совсем не удовлетворен, 5 - полностью удовлетворен).",
    "ans": [
      {
        "ans_id": 1,
        "text": "1"
      },
      {
        "ans_id": 2,
        "text": "2"
      },
      {
        "ans_id": 3,
        "text": "3"
      },
      {
        "ans_id": 4,
        "text": "4"
      },
      {
        "ans_id": 5,
        "text": "5"
      }
    ]
  },
  {
    "q_id": 11,
    "text": "Достаточно ли времени в учебном плане было отведено на изучение дисциплин?",
    "ans": [
      {
        "ans_id": 1,
        "text": "Нет"
      },
      {
        "ans_id": 2,
        "text": "Да"
      }
    ]
  },
  {
    "q_id": 12,
    "text": "Достаточно ли времени в учебном плане было отведено на самостоятельную работу?",
    "ans": [
      {
        "ans_id": 1,
        "text": "Нет"
      },
      {
        "ans_id": 2,
        "text": "Да"
      }
    ]
  },
  {
    "q_id": 14,
    "text": "Оцените использованные методы и способы контроля и проверки знаний  по шкале от 1 до 5, где 1 - совсем не удовлетворен, 5 - полностью удовлетворен).",
    "ans": [
      {
        "ans_id": 1,
        "text": "1"
      },
      {
        "ans_id": 2,
        "text": "2"
      },
      {
        "ans_id": 3,
        "text": "3"
      },
      {
        "ans_id": 4,
        "text": "4"
      },
      {
        "ans_id": 5,
        "text": "5"
      }
    ]
  },
  {
    "q_id": 15,
    "text": "Нуждались ли вы в обратной связи?",
    "ans": [
      {
        "ans_id": 1,
        "text": "Нет"
      },
      {
        "ans_id": 2,
        "text": "Да"
      }
    ]
  },
  {
    "q_id": 16,
    "text": "Оцените уровень удовлетворенности обратной связью по шкале от 1 до 5, где 1 - совсем не удовлетворен, 5 - полностью удовлетворен).",
    "ans": [
      {
        "ans_id": 1,
        "text": "1"
      },
      {
        "ans_id": 2,
        "text": "2"
      },
      {
        "ans_id": 3,
        "text": "3"
      },
      {
        "ans_id": 4,
        "text": "4"
      },
      {
        "ans_id": 5,
        "text": "5"
      }
    ]
  },
  {
    "q_id": 17,
    "text": "Оцените уровень удовлетворенности обучением по шкале от 1 до 5, где 1 - совсем не удовлетворен, 5 - полностью удовлетворен).",
    "ans": [
      {
        "ans_id": 1,
        "text": "1"
      },
      {
        "ans_id": 2,
        "text": "2"
      },
      {
        "ans_id": 3,
        "text": "3"
      },
      {
        "ans_id": 4,
        "text": "4"
      },
      {
        "ans_id": 5,
        "text": "5"
      }
    ]
  },
  {
    "q_id": 18,
    "text": "Есть ли у Вас предложения по улучшению качества реализации дистанционного обучения. ",
    "ans": [
      {
        "ans_id": 1,
        "text": "Нет"
      },
      {
        "ans_id": 2,
        "text": "Да"
      }
    ]
  }
]